NitroDec/NitroDec.py
NitroDec/__init__.py
nitrodec-0.1.4.dist-info/licenses/LICENSE
nitrodec-0.1.4.dist-info/METADATA
nitrodec-0.1.4.dist-info/WHEEL
nitrodec-0.1.4.dist-info/top_level.txt
nitrodec-0.1.4.dist-info/RECORD
