Metadata-Version: 2.4
Name: NitroDec
Version: 0.1.4
Summary: Decorator For Starlette, FastAPI style Decorators
Home-page: https://github.com/yuvrajmodz/NitroDec
Author: @Nactire
Author-email: yuvrajmodz@gmail.com
Classifier: Programming Language :: Python :: 3
Classifier: License :: OSI Approved :: MIT License
Classifier: Operating System :: OS Independent
Requires-Python: >=3.8
License-File: LICENSE
Requires-Dist: starlette[full]
Requires-Dist: uvicorn
Dynamic: author
Dynamic: author-email
Dynamic: classifier
Dynamic: description
Dynamic: description-content-type
Dynamic: home-page
Dynamic: license-file
Dynamic: requires-dist
Dynamic: requires-python
Dynamic: summary
